Flask_Mailer-0.3.7-py2.7-nspkg.pth
Flask_Mailer-0.3.7.dist-info/DESCRIPTION.rst
Flask_Mailer-0.3.7.dist-info/METADATA
Flask_Mailer-0.3.7.dist-info/metadata.json
Flask_Mailer-0.3.7.dist-info/namespace_packages.txt
Flask_Mailer-0.3.7.dist-info/RECORD
Flask_Mailer-0.3.7.dist-info/top_level.txt
Flask_Mailer-0.3.7.dist-info/WHEEL
flaskext/mailer/__init__.py
flaskext/mailer/compat.py
flaskext/mailer/mail.py
flaskext/mailer/util.py
flaskext/mailer/backends/__init__.py
flaskext/mailer/backends/base.py
flaskext/mailer/backends/dummy.py
flaskext/mailer/backends/smtp.py
