Metadata-Version: 2.0
Name: Flask-Mailer
Version: 0.3.7
Summary: A Flask extension for sending emails with pluggable backends.
Home-page: https://github.com/vitalk/flask-mailer
Author: Vital Kudzelka
Author-email: vital.kudzelka@gmail.com
License: BSD
Download-URL: https://github.com/vitalk/flask-mailer/tarball/0.3.7
Keywords: flask mail smtp
Platform: any
Classifier: Development Status :: 3 - Alpha
Classifier: Environment :: Web Environment
Classifier: Intended Audience :: Developers
Classifier: License :: OSI Approved :: BSD License
Classifier: Operating System :: OS Independent
Classifier: Programming Language :: Python
Classifier: Topic :: Internet :: WWW/HTTP :: Dynamic Content
Classifier: Topic :: Software Development :: Libraries :: Python Modules
Requires-Dist: Flask
